[
  {
    "v": 1,
    "t": 3
  },
  {
    "v": 2,
    "t": 10
  },
  {
    "v": 3,
    "t": 18
  },
  {
    "v": 4,
    "t": 25
  },
  {
    "v": 5,
    "t": 32
  },
  {
    "v": 6,
    "t": 38
  },
  {
    "v": 7,
    "t": 45
  },
  {
    "v": 8,
    "t": 51
  },
  {
    "v": 9,
    "t": 58
  },
  {
    "v": 10,
    "t": 64
  },
  {
    "v": 11,
    "t": 71
  },
  {
    "v": 12,
    "t": 77
  },
  {
    "v": 13,
    "t": 83
  },
  {
    "v": 14,
    "t": 90
  },
  {
    "v": 15,
    "t": 96
  },
  {
    "v": 16,
    "t": 103
  },
  {
    "v": 17,
    "t": 110
  },
  {
    "v": 18,
    "t": 116
  },
  {
    "v": 19,
    "t": 124
  },
  {
    "v": 20,
    "t": 130
  },
  {
    "v": 21,
    "t": 137
  },
  {
    "v": 22,
    "t": 143
  },
  {
    "v": 23,
    "t": 150
  },
  {
    "v": 24,
    "t": 157
  },
  {
    "v": 25,
    "t": 165
  },
  {
    "v": 26,
    "t": 171
  },
  {
    "v": 27,
    "t": 178
  },
  {
    "v": 28,
    "t": 184
  },
  {
    "v": 29,
    "t": 191
  },
  {
    "v": 30,
    "t": 197
  },
  {
    "v": 31,
    "t": 204
  },
  {
    "v": 32,
    "t": 211
  },
  {
    "v": 33,
    "t": 217
  },
  {
    "v": 34,
    "t": 225
  },
  {
    "v": 35,
    "t": 232
  },
  {
    "v": 36,
    "t": 238
  },
  {
    "v": 37,
    "t": 246
  },
  {
    "v": 38,
    "t": 252
  },
  {
    "v": 39,
    "t": 259
  },
  {
    "v": 40,
    "t": 265
  },
  {
    "v": 41,
    "t": 271
  },
  {
    "v": 42,
    "t": 278
  },
  {
    "v": 43,
    "t": 284
  },
  {
    "v": 44,
    "t": 291
  },
  {
    "v": 45,
    "t": 299
  },
  {
    "v": 46,
    "t": 305
  },
  {
    "v": 47,
    "t": 314
  },
  {
    "v": 48,
    "t": 320
  },
  {
    "v": 49,
    "t": 326
  },
  {
    "v": 50,
    "t": 332
  },
  {
    "v": 51,
    "t": 339
  },
  {
    "v": 52,
    "t": 345
  },
  {
    "v": 53,
    "t": 352
  },
  {
    "v": 54,
    "t": 358
  },
  {
    "v": 55,
    "t": 365
  },
  {
    "v": 56,
    "t": 372
  },
  {
    "v": 57,
    "t": 379
  },
  {
    "v": 58,
    "t": 386
  },
  {
    "v": 59,
    "t": 393
  },
  {
    "v": 60,
    "t": 399
  },
  {
    "v": 61,
    "t": 407
  },
  {
    "v": 62,
    "t": 413
  },
  {
    "v": 63,
    "t": 419
  },
  {
    "v": 64,
    "t": 427
  },
  {
    "v": 65,
    "t": 434
  },
  {
    "v": 66,
    "t": 441
  },
  {
    "v": 67,
    "t": 448
  },
  {
    "v": 68,
    "t": 455
  },
  {
    "v": 69,
    "t": 462
  },
  {
    "v": 70,
    "t": 468
  },
  {
    "v": 71,
    "t": 473
  },
  {
    "v": 72,
    "t": 480
  },
  {
    "v": 73,
    "t": 487
  },
  {
    "v": 74,
    "t": 494
  },
  {
    "v": 75,
    "t": 502
  },
  {
    "v": 76,
    "t": 509
  },
  {
    "v": 77,
    "t": 515
  },
  {
    "v": 78,
    "t": 522
  }
]